{
	"name": "configParameter",
	"properties": {
		"linkedServiceName": {
			"referenceName": "dls_con",
			"type": "LinkedServiceReference"
		},
		"annotations": [],
		"type": "DelimitedText",
		"typeProperties": {
			"location": {
				"type": "AzureBlobFSLocation",
				"fileName": "config.csv",
				"fileSystem": "parameters"
			},
			"columnDelimiter": ";",
			"escapeChar": "\\",
			"firstRowAsHeader": true,
			"quoteChar": "\""
		},
		"schema": [
			{
				"name": "path;catalogo;storageName;cluster_id;credential_;domain;secretname;cluster",
				"type": "String"
			}
		]
	}
}